rdsline/__init__.py
rdsline/cli.py
rdsline/results.py
rdsline/settings.py
rdsline/version.py
rdsline/connections/__init__.py
rdsline/connections/rds_secretsmanager.py
rdsline-0.4.5.dist-info/LICENSE.txt
rdsline-0.4.5.dist-info/METADATA
rdsline-0.4.5.dist-info/WHEEL
rdsline-0.4.5.dist-info/entry_points.txt
rdsline-0.4.5.dist-info/top_level.txt
rdsline-0.4.5.dist-info/RECORD
